{
  "produto": "GlamoreJoias-TREINAMENTO-COMPLETO-PROFISSIONAL-V5",
  "versao": "5.0.0",
  "destino": "repositorio separado tsvalencio-IA/treinamento",
  "sistema_oficial_modificado": false,
  "firebase_oficial": false,
  "mecanismos": [
    "camera fixa 100dvh",
    "localizacao exata sem fallback generico",
    "scroll automatico interno",
    "zoom do render real",
    "spotlight calculado sobre o elemento",
    "audio iniciado somente depois do enquadramento",
    "legenda dinamica que evita o alvo",
    "bloqueio de rolagem manual",
    "pausa segura quando um elemento nao e encontrado"
  ],
  "narracao": "ensina somente como usar o sistema, sem explicar o motor do treinamento"
}