{
  "produto": "GlamoreJoias-TREINAMENTO-PRATICO-FINAL",
  "versao": "10.0.0",
  "repositorio_destino": "tsvalencio-IA/treinamento",
  "repositorio_oficial_modificado": false,
  "firebase_oficial": false,
  "aulas": 10,
  "modelo": "simulador controlado com alvos exclusivos; não depende de localizar textos dinâmicos",
  "fluxos": [
    "inventario",
    "entrada_manual",
    "venda",
    "venda_parcial",
    "alerta",
    "producao_aprovada",
    "producao_pronta",
    "excedente",
    "relatorios",
    "auditoria",
    "estorno_venda",
    "estorno_inventario",
    "corrigir_status_pdf",
    "estorno_producao",
    "usuarios_cargos_regras"
  ]
}